{"metadata":{"analyst":"Stephen Ni-Hahn","composer":"Pachelbel","title":"Primi_3","subtitle":"None","commentary":"None","author":"Rico"},"key":"1f","trebleNotes":{"pitchNames":["_","_","A4","A4","A4","_","G4","G4","_","F4","F4","_","E4","E4","_","D4","D4","C4","D4"],"depths":[0,0,4,0,0,0,2,0,0,1,0,0,3,0,0,1,0,2,4],"selected":[],"ursatz":[2,18],"scaleDegree":[0,0,0,0,0,0,0,0,0,0,0,0,0,0,0,0,0,0,0],"flagged":[],"sharps":[17],"flats":[],"naturals":[],"parenthetical":[]},"bassNotes":{"pitchNames":["D4","D4","_","_","_","D4","_","_","C4","_","_","B3","_","_","A3","_","_","_","D4"],"depths":[4,0,0,0,0,0,0,0,2,0,0,1,0,0,3,0,0,0,4],"selected":[0],"ursatz":[0,18],"scaleDegree":[3,0,0,0,0,0,0,0,0,0,0,0,0,0,0,0,0,0,0],"flagged":[],"sharps":[],"flats":[],"naturals":[11],"parenthetical":[]},"innerTrebleNotes":{"pitchNames":["_","_","_","_","_","_","_","_","_","_","_","_","_","_","_","_","_","_","_"],"depths":[0,1,0,0,0,0,0,0,0,0,0,0,0,0,0,0,0,0,0],"selected":[],"ursatz":[],"scaleDegree":[0,0,0,0,0,0,0,0,0,0,0,0,0,0,0,0,0,0,0],"flagged":[],"sharps":[],"flats":[],"naturals":[],"parenthetical":[]},"innerBassNotes":{"pitchNames":["_","_","_","_","_","_","_","_","_","_","_","_","_","_","_","_","_","_","_"],"depths":[0,0,0,0,0,0,0,0,0,0,0,0,0,0,0,0,0,0,0],"selected":[],"ursatz":[],"scaleDegree":[0,0,0,0,0,0,0,0,0,0,0,0,0,0,0,0,0,0,0],"flagged":[],"sharps":[],"flats":[],"naturals":[],"parenthetical":[]},"noteConnections":{"voiceExchangesFromTreble":[],"voiceExchangesFromBass":[]}}